lykkellemainportfolio/__init__.py
lykkellemainportfolio/mainindexcreationeod.py
lykkellemainportfolio/mainindustryportfolio.py
lykkellemainportfolio/mainoptimalportfolioeod.py
lykkellemainportfolio-0.1.1.dist-info/LICENSE
lykkellemainportfolio-0.1.1.dist-info/METADATA
lykkellemainportfolio-0.1.1.dist-info/WHEEL
lykkellemainportfolio-0.1.1.dist-info/top_level.txt
lykkellemainportfolio-0.1.1.dist-info/RECORD
